ss_logging_tool/__init__.py
ss_logging_tool/logger.py
python_ss_logging_tool-0.1.2.dist-info/METADATA
python_ss_logging_tool-0.1.2.dist-info/WHEEL
python_ss_logging_tool-0.1.2.dist-info/top_level.txt
python_ss_logging_tool-0.1.2.dist-info/RECORD
