Metadata-Version: 2.1
Name: python-ss-logging-tool
Version: 0.1.2
Summary: A simple logger package
Home-page: https://github.com/yourusername/mypackage
Author: Jimmy
Author-email: jimm@xxx.com
Classifier: Development Status :: 3 - Alpha
Classifier: License :: OSI Approved :: MIT License
Classifier: Programming Language :: Python :: 3
Classifier: Programming Language :: Python :: 3.6
Classifier: Programming Language :: Python :: 3.7
Classifier: Programming Language :: Python :: 3.8
Requires-Dist: pino
Requires-Dist: nanoid
